mezzanine_api/__init__.py
mezzanine_api/apps.py
mezzanine_api/middleware.py
mezzanine_api/mixins.py
mezzanine_api/pagination.py
mezzanine_api/permissions.py
mezzanine_api/serializers.py
mezzanine_api/settings.py
mezzanine_api/urls.py
mezzanine_api/views.py
mezzanine_api/project_template/__init__.py
mezzanine_api/project_template/manage.py
mezzanine_api/project_template/project_name/__init__.py
mezzanine_api/project_template/project_name/local_settings.py.template
mezzanine_api/project_template/project_name/settings.py
mezzanine_api/project_template/project_name/urls.py
mezzanine_api/project_template/templates/index.html
mezzanine_api/static/mezzanine_api/css/default.css
mezzanine_api/static/mezzanine_api/img/mezzanine_api_logo.png
mezzanine_api/templates/rest_framework/api.html
mezzanine_api/templates/rest_framework/login.html
mezzanine_api/templatetags/__init__.py
mezzanine_api/templatetags/mezzanine_api.py
mezzanine_api-0.7.1.dist-info/LICENSE
mezzanine_api-0.7.1.dist-info/METADATA
mezzanine_api-0.7.1.dist-info/WHEEL
mezzanine_api-0.7.1.dist-info/top_level.txt
mezzanine_api-0.7.1.dist-info/RECORD
