Metadata-Version: 2.1
Name: mezzanine-api
Version: 0.7.1
Summary: A RESTful web API for Mezzanine CMS.
Home-page: http://gcushen.github.io/mezzanine-api
Author: George Cushen
Author-email: mezzanine-users@googlegroups.com
License: MIT
Keywords: mezzanine cms api rest restful web
Platform: UNKNOWN
Classifier: Development Status :: 5 - Production/Stable
Classifier: Environment :: Web Environment
Classifier: Framework :: Django
Classifier: Intended Audience :: Developers
Classifier: License :: OSI Approved :: MIT License
Classifier: Operating System :: OS Independent
Classifier: Programming Language :: Python
Classifier: Programming Language :: Python :: 3
Classifier: Programming Language :: Python :: 3.6
Classifier: Topic :: Internet :: WWW/HTTP
Classifier: Topic :: Internet :: WWW/HTTP :: Dynamic Content
Classifier: Topic :: Internet :: WWW/HTTP :: Site Management
Classifier: Topic :: Software Development :: Libraries :: Python Modules
Requires-Dist: Mezzanine (>=4.3.0)
Requires-Dist: django-rest-swagger (<3.0.0,>=2.1.1)
Requires-Dist: djangorestframework (<4.0.0,>=3.7.1)
Requires-Dist: django-filter (>=2.0.0)
Requires-Dist: django-oauth-toolkit (<1.2.0,>=1.1.2)
